[
    {
        "id": 1,
        "nombre": "Killer Bees",
        "img": "1.jpg"
    },
    {
        "id": 2,
        "nombre": "Aphids",
        "img": "2.jpg"
    },
    {
        "id": 3,
        "nombre": "Armyworms",
        "img": "3.png"
    },
    {
        "id": 4,
        "nombre": "Brown Marmorated Stink Bugs",
        "img": "4.jpg"
    },
    {
        "id": 5,
        "nombre": "Cabbage Loopers",
        "img": "5.png"
    },
    {
        "id": 6,
        "nombre": "Citrus Canker",
        "img": "6.jpg"
    },
    {
        "id": 7,
        "nombre": "Colorado Potato Beetles",
        "img": "7.jpg"
    },
    {
        "id": 8,
        "nombre": "Corn Borers",
        "img": "8.png"
    },
    {
        "id": 9,
        "nombre": "Corn Earworms",
        "img": "9.jpg"
    },
    {
        "id": 10,
        "nombre": "Fall Armyworms",
        "img": "10.png"
    },
    {
        "id": 11,
        "nombre": "Fruit Flies",
        "img": "11.jpg"
    },
    {
        "id": 12,
        "nombre": "Spider Mites",
        "img": "12.png"
    },
    {
        "id": 13,
        "nombre": "Thrips",
        "img": "13.jpg"
    },
    {
        "id": 14,
        "nombre": "Tomato Hornworms",
        "img": "14.jpg"
    },
    {
        "id": 15,
        "nombre": "Western Corn Rootworms",
        "img": "15.jpg"
    }

]